pandas_query_sql-0.8.1.dist-info/METADATA
pandas_query_sql-0.8.1.dist-info/WHEEL
pandas_query_sql-0.8.1.dist-info/licenses/AUTHORS.md
pandas_query_sql-0.8.1.dist-info/licenses/LICENSE.txt
pandasql/__init__.py
pandasql/data/births.csv
pandasql/data/births_by_month.csv
pandasql/data/meat.csv
pandasql/py.typed
pandasql/sqldf.py
pandas_query_sql-0.8.1.dist-info/RECORD
