Metadata-Version: 2.1
Name: pandas_query_sql
Version: 0.8.1
Summary: sqldf for pandas
Author-Email: Alexander Plavin <alexander@plav.in>, Greg Lamp <lamp.greg@gmail.com>, Michael Dempsey <bluestealth@bluestealth.pw>
License: MIT
Classifier: License :: OSI Approved :: MIT License
Project-URL: Homepage, https://github.com/bluestealth/pandasql/
Requires-Python: >=3.8
Requires-Dist: numpy
Requires-Dist: packaging
Requires-Dist: pandas
Requires-Dist: sqlalchemy
Requires-Dist: psycopg2; extra == "postgresql"
Requires-Dist: psycopg2-binary; extra == "postgresql-binary"
Requires-Dist: black; extra == "linters"
Requires-Dist: ruff; extra == "linters"
Requires-Dist: pytest; extra == "testing"
Requires-Dist: psycopg2-binary; extra == "testing"
Provides-Extra: postgresql
Provides-Extra: postgresql-binary
Provides-Extra: linters
Provides-Extra: testing
